pymillion/__init__.py
pymillion/banner.py
pymillion/cli.py
pymillion/core.py
pymillion/exceptions.py
pymillion/exporters.py
pymillion/generator.py
pymillion/loaders.py
pymillion/sender.py
pymillion/server.py
pymillion/utils.py
pymillion-0.0.1.dist-info/METADATA
pymillion-0.0.1.dist-info/WHEEL
pymillion-0.0.1.dist-info/entry_points.txt
pymillion-0.0.1.dist-info/top_level.txt
pymillion-0.0.1.dist-info/RECORD
