Metadata-Version: 2.4
Name: pymillion
Version: 0.0.1
Requires-Dist: rich
Requires-Dist: flask
Dynamic: requires-dist
